oneclickai/__init__.py
oneclickai/core.py
oneclickai/YOLO/__init__.py
oneclickai/YOLO/createDataAugumentation.py
oneclickai/YOLO/createDataGenerator.py
oneclickai/YOLO/drawImage.py
oneclickai/YOLO/fit.py
oneclickai/YOLO/labelDecode.py
oneclickai/YOLO/labelEncode.py
oneclickai/YOLO/load_model.py
oneclickai/YOLO/predict.py
oneclickai/YOLO/readTxt.py
oneclickai/YOLO/stream.py
oneclickai/YOLO/yoloLoss.py
oneclickai/YOLO/yoloModel8.py
test/__init__.py
test/test.py
test/test_core.py
test/test_fit.py
test/test_predict.py
test/test_predict2.py
test/test_stream.py
oneclickai-0.1.10.dist-info/METADATA
oneclickai-0.1.10.dist-info/WHEEL
oneclickai-0.1.10.dist-info/top_level.txt
oneclickai-0.1.10.dist-info/RECORD
