Metadata-Version: 2.1
Name: oneclickai
Version: 0.1.10
Summary: OneclickAI package for learning AI with python
Home-page: https://oneclickai.co.kr
Author: Seung Oh
Author-email: osy044@naver.com
Keywords: oneclick,clickai,learning ai,ai model,ai,ai package,oneclickai,oneclickai package
Classifier: Programming Language :: Python :: 3.9
Classifier: Programming Language :: Python :: 3.10
Classifier: Programming Language :: Python :: 3.11
Classifier: Programming Language :: Python :: 3.12
Requires-Python: >=3.7
Requires-Dist: openpyxl
Requires-Dist: gdown
Requires-Dist: tensorflow ==2.13.0 ; python_version < "3.12"
Requires-Dist: torch ==2.1 ; python_version < "3.12"
Requires-Dist: torchvision ==0.16 ; python_version < "3.12"
Requires-Dist: torchaudio ==2.1 ; python_version < "3.12"
Requires-Dist: opencv-python ==4.10.0.84 ; python_version < "3.12"
Requires-Dist: numpy ==1.24.3 ; python_version < "3.12"
Requires-Dist: pandas ==2.2.3 ; python_version < "3.12"
Requires-Dist: ultralytics ==8.3.28 ; python_version < "3.12"
Requires-Dist: flatbuffers ==24.3.25 ; python_version < "3.12"
Requires-Dist: tensorflow ; python_version >= "3.12"
Requires-Dist: torch ; python_version >= "3.12"
Requires-Dist: torchvision ; python_version >= "3.12"
Requires-Dist: torchaudio ; python_version >= "3.12"
Requires-Dist: opencv-python ; python_version >= "3.12"
Requires-Dist: numpy ; python_version >= "3.12"
Requires-Dist: pandas ; python_version >= "3.12"
Requires-Dist: ultralytics ; python_version >= "3.12"
